netzcfg/README.MD
netzcfg/__init__.py
netzcfg/requirements.txt
netzcfg/thirdparty.json
netzcfg-0.10.dist-info/LICENSE.rst
netzcfg-0.10.dist-info/METADATA
netzcfg-0.10.dist-info/WHEEL
netzcfg-0.10.dist-info/top_level.txt
netzcfg-0.10.dist-info/RECORD
