Metadata-Version: 2.1
Name: netzcfg
Version: 0.10
Summary: Retrieves network adapter configuration information using Windows Management Instrumentation (WMI) and return it as a Pandas DataFrame.
Home-page: https://github.com/hansalemaos/netzcfg
Author: Johannes Fischer
Author-email: aulasparticularesdealemaosp@gmail.com
License: MIT
Keywords: wmi,network,config
Classifier: Development Status :: 4 - Beta
Classifier: Programming Language :: Python :: 3 :: Only
Classifier: Programming Language :: Python :: 3.10
Classifier: Topic :: Software Development :: Libraries :: Python Modules
Classifier: Topic :: Utilities
License-File: LICENSE.rst
Requires-Dist: WMI
Requires-Dist: pandas
